{"assets":{"E1E564043651FA65D0202B4EF0A26176":{"type":"texture","index":19,"assetRequest":{"type":"slide","state":"incoming","slide":"A5464B77-8EE4-4F68-91D1-20345CA81635"},"url":"assets/E1E564043651FA65D0202B4EF0A26176.svg","width":1024,"height":768},"DA4C322E2318463ABF43B52EE76164AB":{"type":"texture","index":18,"assetRequest":{"type":"slide","state":"outgoing","slide":"D8AC2D37-8944-4796-AF0E-4D7C53CDE59E"},"url":"assets/DA4C322E2318463ABF43B52EE76164AB.svg","width":1024,"height":768}},"events":[{"effects":[{"beginTime":0,"baseLayer":{"animations":[],"initialState":{"affineTransform":[1,0,0,1,0,0],"masksToBounds":true,"rotation":0,"scale":1,"position":{"pointX":512,"pointY":384},"width":1024,"sublayerTransform":[1,0,0,0,0,1,0,0,0,0,1,0,0,0,0,1],"contentsRect":{"y":0,"x":0,"width":1,"height":1},"opacity":1,"edgeAntialiasingMask":0,"height":768,"hidden":false,"anchorPoint":{"pointX":0.5,"pointY":0.5}},"objectID":"0","layers":[{"animations":[],"initialState":{"affineTransform":[1,0,0,1,0,0],"masksToBounds":false,"rotation":0,"scale":1,"position":{"pointX":512,"pointY":384},"width":1024,"sublayerTransform":[1,0,0,0,0,1,0,0,0,0,1,-0.0004922987690640373,0,0,0,1],"contentsRect":{"y":0,"x":0,"width":1,"height":1},"opacity":1,"edgeAntialiasingMask":15,"height":768,"hidden":false,"anchorPoint":{"pointX":0.5,"pointY":0.5}},"layers":[{"animations":[],"layers":[],"initialState":{"affineTransform":[1,0,0,1,0,0],"masksToBounds":false,"rotation":0,"scale":1,"position":{"pointX":512,"pointY":384},"width":1024,"sublayerTransform":[1,0,0,0,0,1,0,0,0,0,1,0,0,0,0,1],"contentsRect":{"y":0,"x":0,"width":1,"height":1},"opacity":1,"edgeAntialiasingMask":0,"height":768,"hidden":false,"anchorPoint":{"pointX":0.5,"pointY":0.5}},"texture":"E1E564043651FA65D0202B4EF0A26176"},{"animations":[{"from":{"scalar":false},"beginTime":0,"repeatCount":0,"fillMode":"both","property":"hidden","duration":0.01,"to":{"scalar":true}}],"layers":[],"initialState":{"affineTransform":[1,0,0,1,0,0],"masksToBounds":false,"rotation":0,"scale":1,"position":{"pointX":512,"pointY":384},"width":1024,"sublayerTransform":[1,0,0,0,0,1,0,0,0,0,1,0,0,0,0,1],"contentsRect":{"y":0,"x":0,"width":1,"height":1},"opacity":1,"edgeAntialiasingMask":0,"height":768,"hidden":false,"anchorPoint":{"pointX":0.5,"pointY":0.5}},"texture":"DA4C322E2318463ABF43B52EE76164AB"}]}]},"effects":[],"duration":0.01,"type":"transition","name":"none","objectID":"0"}],"automaticPlay":false,"hyperlinks":[],"accessibility":[{"text":"setTimeout(function () {","targetRectangle":{"y":366.1171875,"x":200.17578125,"width":337.01484375,"height":29}},{"text":"  console.log('this will never be called!')","targetRectangle":{"y":369.0171875432134,"x":200.17578125,"width":603.8182617187499,"height":61.75999879837036}},{"text":"}, 100)","targetRectangle":{"y":404.6771863847971,"x":200.17578125,"width":98.29599609374998,"height":61.75999879837036}},{"text":"var i = 0","targetRectangle":{"y":475.9971840679646,"x":200.17578125,"width":126.38056640625,"height":61.75999879837036}},{"text":"while (true) {","targetRectangle":{"y":511.6571829095483,"x":200.17578125,"width":196.5919921875,"height":61.75999879837036}},{"text":"  // this indefinite loop will ","targetRectangle":{"y":547.317181751132,"x":200.17578125,"width":435.3108398437498,"height":61.75999879837036}},{"text":"  // make this phase last forever","targetRectangle":{"y":582.9771805927157,"x":200.17578125,"width":463.3954101562497,"height":61.75999879837036}},{"text":"  i++","targetRectangle":{"y":618.6371794342995,"x":200.17578125,"width":70.21142578125,"height":61.75999879837036}},{"text":"}","targetRectangle":{"y":654.2971782758832,"x":200.17578125,"width":14.04228515624999,"height":61.75999879837036}},{"text":"Blocking the Event Loop","targetRectangle":{"y":58,"x":80.59759999999977,"width":862.8048000000003,"height":95}},{"text":"When a single phase of the event loop is too long, it will prevent all subsequent phases from executing.","targetRectangle":{"y":217,"x":79,"width":869.3678000000001,"height":92}}],"baseLayer":{"animations":[],"initialState":{"affineTransform":[1,0,0,1,0,0],"masksToBounds":true,"rotation":0,"scale":1,"position":{"pointX":512,"pointY":384},"width":1024,"sublayerTransform":[1,0,0,0,0,1,0,0,0,0,1,0,0,0,0,1],"contentsRect":{"y":0,"x":0,"width":1,"height":1},"opacity":1,"edgeAntialiasingMask":0,"height":768,"hidden":false,"anchorPoint":{"pointX":0.5,"pointY":0.5}},"objectID":"0","layers":[{"animations":[],"initialState":{"affineTransform":[1,0,0,1,0,0],"masksToBounds":false,"rotation":0,"scale":1,"position":{"pointX":512,"pointY":384},"width":1024,"sublayerTransform":[1,0,0,0,0,1,0,0,0,0,1,-0.0004922987690640373,0,0,0,1],"contentsRect":{"y":0,"x":0,"width":1,"height":1},"opacity":1,"edgeAntialiasingMask":15,"height":768,"hidden":false,"anchorPoint":{"pointX":0.5,"pointY":0.5}},"layers":[{"animations":[],"layers":[],"initialState":{"affineTransform":[1,0,0,1,0,0],"masksToBounds":false,"rotation":0,"scale":1,"position":{"pointX":512,"pointY":384},"width":1024,"sublayerTransform":[1,0,0,0,0,1,0,0,0,0,1,0,0,0,0,1],"contentsRect":{"y":0,"x":0,"width":1,"height":1},"opacity":1,"edgeAntialiasingMask":0,"height":768,"hidden":false,"anchorPoint":{"pointX":0.5,"pointY":0.5}},"texture":"DA4C322E2318463ABF43B52EE76164AB"}]}]}}]}